aws_arn/__init__.py
aws_arn/data.py
aws_arn/get_parser.py
aws_arn/main.py
aws_arn-0.0.19.dist-info/LICENSE
aws_arn-0.0.19.dist-info/METADATA
aws_arn-0.0.19.dist-info/WHEEL
aws_arn-0.0.19.dist-info/entry_points.txt
aws_arn-0.0.19.dist-info/top_level.txt
aws_arn-0.0.19.dist-info/RECORD
