Metadata-Version: 2.1
Name: aws-arn
Version: 0.0.19
Summary: A library to work with AWS ARNs
Author: Gabriel Alejandro Soltz
Author-email: gabriel@3ops.com
Project-URL: Source code, https://github.com/gabrielsoltz/aws-arn
Classifier: Development Status :: 3 - Alpha
Classifier: Intended Audience :: Developers
Classifier: Programming Language :: Python :: 3
Classifier: License :: OSI Approved :: MIT License
Classifier: Operating System :: OS Independent
License-File: LICENSE
